[
    {"grupo": "A","local": "QATAR", "visitante": "ECUADOR", "description": "Est. Icónico, Lusail - Martes 22 de Noviembre (22/11/2022) - 08:00hs UTC"},
    {"grupo": "A","local": "QATAR", "visitante": "ECUADOR", "description": "Est. Icónico, Lusail - Martes 22 de Noviembre (22/11/2022) - 08:00hs UTC"},
    {"grupo": "A","local": "QATAR", "visitante": "ECUADOR", "description": "Est. Icónico, Lusail - Martes 22 de Noviembre (22/11/2022) - 08:00hs UTC"},
    {"grupo": "A","local": "QATAR", "visitante": "ECUADOR", "description": "Est. Icónico, Lusail - Martes 22 de Noviembre (22/11/2022) - 08:00hs UTC"},
    {"grupo": "A","local": "QATAR", "visitante": "ECUADOR", "description": "Est. Icónico, Lusail - Martes 22 de Noviembre (22/11/2022) - 08:00hs UTC"},
    {"grupo": "A","local": "QATAR", "visitante": "ECUADOR", "description": "Est. Icónico, Lusail - Martes 22 de Noviembre (22/11/2022) - 08:00hs UTC"}
]